CAST_panel/__init__.py
cast_panel-1.0.2.dist-info/METADATA
cast_panel-1.0.2.dist-info/WHEEL
cast_panel-1.0.2.dist-info/licenses/LICENSE
cast_panel-1.0.2.dist-info/RECORD
