Metadata-Version: 2.4
Name: CAST_panel
Version: 1.0.2
Summary: Causal inference for staggered treatments in panel
Author-email: Eric Xia <ericzxia@gmail.com>
License-File: LICENSE
Classifier: License :: OSI Approved :: MIT License
Classifier: Operating System :: OS Independent
Classifier: Programming Language :: Python :: 3
Requires-Python: >=3.8
